mapafiscal/__init__.py
mapafiscal/application/__init__.py
mapafiscal/application/cenario_builder.py
mapafiscal/application/excel_exporter.py
mapafiscal/application/templates/mapafiscal.xlsx
mapafiscal/domain/__init__.py
mapafiscal/domain/aggregates/__init__.py
mapafiscal/domain/aggregates/cenario_fiscal.py
mapafiscal/domain/aggregates/classe_fiscal.py
mapafiscal/domain/aggregates/classe_st.py
mapafiscal/domain/aggregates/mapa_fiscal.py
mapafiscal/domain/aggregates/operacao_fiscal.py
mapafiscal/domain/common/__init__.py
mapafiscal/domain/common/cst_icms.py
mapafiscal/domain/common/cst_ipi.py
mapafiscal/domain/common/cst_pis_cofins.py
mapafiscal/domain/common/finalidade.py
mapafiscal/domain/common/natureza_operacao.py
mapafiscal/domain/common/perfil_contribuinte.py
mapafiscal/domain/common/regime_especial.py
mapafiscal/domain/common/regime_tributacao.py
mapafiscal/domain/common/tipo_cliente.py
mapafiscal/domain/common/tipo_incidencia.py
mapafiscal/domain/common/uf.py
mapafiscal/domain/entities/__init__.py
mapafiscal/domain/entities/aliquota.py
mapafiscal/domain/entities/cenario_incidencia.py
mapafiscal/domain/entities/excecao_fiscal.py
mapafiscal/domain/entities/pauta_fiscal.py
mapafiscal/domain/entities/tributos.py
mapafiscal/domain/services/__init__.py
mapafiscal/domain/services/contexto_fiscal.py
mapafiscal/domain/services/mapa_fiscal_builder.py
mapafiscal/domain/services/mapa_fiscal_processor.py
mapafiscal/infrastructure/__init__.py
mapafiscal/infrastructure/admin/__init__.py
mapafiscal/infrastructure/admin/manage.py
mapafiscal/infrastructure/persistence/__init__.py
mapafiscal/infrastructure/persistence/json_repository.py
mapafiscal/interfaces/__init__.py
mapafiscal/interfaces/repository.py
mapafiscal/resources/tabelas/tabela_aliquota_icms_estados_v1_001.json
mapafiscal/resources/tabelas/tabela_aliquota_ipi_v1_001.json
mapafiscal/resources/tabelas/tabela_excecao_fiscal_v1_001.json
mapafiscal-0.3.8.dist-info/LICENSE
mapafiscal-0.3.8.dist-info/METADATA
mapafiscal-0.3.8.dist-info/WHEEL
mapafiscal-0.3.8.dist-info/entry_points.txt
mapafiscal-0.3.8.dist-info/top_level.txt
mapafiscal-0.3.8.dist-info/RECORD
