Metadata-Version: 2.1
Name: mapafiscal
Version: 0.3.8
Summary: Gerador de mapa fiscal com base em regras fiscais
Home-page: https://github.com/ismaelnjr/mapafiscal-project.git
Author: Ismael Nascimento
Author-email: ismaelnjr@icloud.com
License: MIT
Keywords: mapa fiscal tributario receita federal
Classifier: Programming Language :: Python :: 3
Classifier: License :: OSI Approved :: MIT License
Classifier: Operating System :: OS Independent
Classifier: Development Status :: 4 - Beta
Classifier: Intended Audience :: Developers
Classifier: Topic :: Software Development :: Build Tools
Requires-Python: >=3.7
License-File: LICENSE
Requires-Dist: openpyxl
